Workbook

Sheet Categoria x Puesto
A1: Column1 | B1: Category | C1: Workplace | D1: Location | E1: Department | F1: Type | G1: Salary
A2: 0 | B2: Business Analyst | C2: Remote | D2: United Kingdom | E2: Operations | F2: Full time | G2: =RANDBETWEEN(6500,12000) -> 10948
A3: 1 | B3: Business Analyst | C3: Remote | D3: Makati, Metro Manila, Philippines | E3: Aux HQ | F3: Full time | G3: =RANDBETWEEN(6500,12000) -> 9322
A4: 2 | B4: Business Analyst | C4: On-site | D4: Al-Dajeej, Al Farwaniyah Governorate, Kuwait | E4: PWC Technologies | F4: Full time | G4: =RANDBETWEEN(6500,12000) -> 9271
A5: 3 | B5: Business Analyst | C5: On-site | D5: London, England, United Kingdom | E5: Consultants, Advisory | F5: Full time | G5: =RANDBETWEEN(6500,12000) -> 7695
A6: 4 | B6: Business Analyst | C6: Remote | D6: United Kingdom | E6: Operations | F6: Full time | G6: =RANDBETWEEN(6500,12000) -> 11498
A7: 5 | B7: Business Analyst | C7: Remote | D7: Makati, Metro Manila, Philippines | E7: Aux HQ | F7: Full time | G7: =RANDBETWEEN(6500,12000) -> 10408
A8: 6 | B8: Business Analyst | C8: On-site | D8: Al-Dajeej, Al Farwaniyah Governorate, Kuwait | E8: PWC Technologies | F8: Full time | G8: =RANDBETWEEN(6500,12000) -> 7145
A9: 7 | B9: Business Analyst | C9: On-site | D9: London, England, United Kingdom | E9: Consultants, Advisory | F9: Full time | G9: =RANDBETWEEN(6500,12000) -> 10074
A10: 8 | B10: Business Analyst | C10: Remote | D10: London, England, United Kingdom | E10: Change & Innovation | G10: =RANDBETWEEN(6500,12000) -> 11959
A11: 9 | B11: Business Analyst | C11: Remote | D11: Makati, Metro Manila, Philippines | E11: Aux HQ | F11: Full time | G11: =RANDBETWEEN(6500,12000) -> 7901
A12: 10 | B12: Business Analyst | C12: On-site | D12: Islamabad, Islamabad Capital Territory, Pakistan | E12: Data & Strategy, Performance Analytics | F12: Full time | G12: =RANDBETWEEN(6500,12000) -> 7248
A13: 11 | B13: Business Analyst | C13: Remote | D13: United States | E13: Computer/Software | F13: Full time | G13: =RANDBETWEEN(6500,12000) -> 10616
A14: 12 | B14: Business Analyst | C14: Hybrid | D14: London, England, United Kingdom | E14: Corporate Affairs | F14: Full time | G14: =RANDBETWEEN(6500,12000) -> 7600
A15: 13 | B15: Business Analyst | C15: Hybrid | D15: London, England, United Kingdom | E15: Technology | F15: Full time | G15: =RANDBETWEEN(6500,12000) -> 11358
A16: 14 | B16: Business Analyst | C16: Hybrid | D16: Cary, North Carolina, United States | E16: 1 - Operations | F16: Full time | G16: =RANDBETWEEN(6500,12000) -> 11064
A17: 15 | B17: Business Analyst | C17: On-site | D17: Overland Park, Kansas, United States | E17: Consulting | F17: Contract | G17: =RANDBETWEEN(6500,12000) -> 8745
A18: 16 | B18: Business Analyst | C18: Remote | D18: Brookfield, Wisconsin, United States | E18: Security - Delivery | F18: Full time | G18: =RANDBETWEEN(6500,12000) -> 8294
A19: 17 | B19: Business Analyst | C19: On-site | D19: Islamabad, Islamabad Capital Territory, Pakistan | E19: Data & Strategy, Digital Analytics | F19: Full time | G19: =RANDBETWEEN(6500,12000) -> 6937
A20: 18 | B20: Business Analyst | C20: Remote | D20: London, England, United Kingdom | E20: Change & Innovation | G20: =RANDBETWEEN(6500,12000) -> 6904
A21: 19 | B21: Business Analyst | C21: Remote | D21: Makati, Metro Manila, Philippines | E21: Aux HQ | F21: Full time | G21: =RANDBETWEEN(6500,12000) -> 10045
A22: 20 | B22: Business Analyst | C22: On-site | D22: Islamabad, Islamabad Capital Territory, Pakistan | E22: Data & Strategy, Performance Analytics | F22: Full time | G22: =RANDBETWEEN(6500,12000) -> 7841
A23: 21 | B23: Business Analyst | C23: Remote | D23: United States | E23: Computer/Software | F23: Full time | G23: =RANDBETWEEN(6500,12000) -> 9121
A24: 22 | B24: Business Analyst | C24: Hybrid | D24: London, England, United Kingdom | E24: Corporate Affairs | F24: Full time | G24: =RANDBETWEEN(6500,12000) -> 11897
A25: 23 | B25: Business Analyst | C25: Hybrid | D25: London, England, United Kingdom | E25: Technology | F25: Full time | G25: =RANDBETWEEN(6500,12000) -> 7119
A26: 24 | B26: Business Analyst | C26: Hybrid | D26: Cary, North Carolina, United States | E26: 1 - Operations | F26: Full time | G26: =RANDBETWEEN(6500,12000) -> 8085
A27: 25 | B27: Business Analyst | C27: On-site | D27: Overland Park, Kansas, United States | E27: Consulting | F27: Contract | G27: =RANDBETWEEN(6500,12000) -> 8470
A28: 26 | B28: Business Analyst | C28: Remote | D28: Brookfield, Wisconsin, United States | E28: Security - Delivery | F28: Full time | G28: =RANDBETWEEN(6500,12000) -> 11679
A29: 27 | B29: Business Analyst | C29: On-site | D29: Islamabad, Islamabad Capital Territory, Pakistan | E29: Data & Strategy, Digital Analytics | F29: Full time | G29: =RANDBETWEEN(6500,12000) -> 10556
A30: 28 | B30: Business Analyst | C30: Remote | D30: Athens, Attica, Greece | E30: DELIV1 | F30: Full time | G30: =RANDBETWEEN(6500,12000) -> 10489
A31: 29 | B31: Business Analyst | C31: On-site | D31: Astana, Aqmola oblısı, Kazakhstan | E31: TECH | F31: Full time | G31: =RANDBETWEEN(6500,12000) -> 9857
A32: 30 | B32: Business Analyst | C32: On-site | D32: North West, England, United Kingdom | E32: Change+ | G32: =RANDBETWEEN(6500,12000) -> 8492
A33: 31 | B33: Business Analyst | C33: Hybrid | D33: Berlin, Berlin, Germany | E33: Business & Organization | G33: =RANDBETWEEN(6500,12000) -> 9767
A34: 32 | B34: Business Analyst | C34: Remote | D34: Washington, District of Columbia, United States | E34: Account Team | F34: Full time | G34: =RANDBETWEEN(6500,12000) -> 7497
A35: 33 | B35: Business Analyst | C35: On-site | D35: Boston, Massachusetts, United States | E35: Delivery | F35: Full time | G35: =RANDBETWEEN(6500,12000) -> 9576
A36: 34 | B36: Business Analyst | C36: On-site | D36: Orlando, Florida, United States | E36: Information Technology | F36: Full time | G36: =RANDBETWEEN(6500,12000) -> 7643
A37: 35 | B37: Business Analyst | C37: On-site | D37: London, England, United Kingdom | E37: Change+ | G37: =RANDBETWEEN(6500,12000) -> 9291
A38: 36 | B38: Business Analyst | C38: Remote | D38: Makati, Metro Manila, Philippines | E38: Aux HQ | F38: Full time | G38: =RANDBETWEEN(6500,12000) -> 10805
A39: 37 | B39: Business Analyst | C39: On-site | D39: Washington, District of Columbia, United States | E39: Labs | F39: Full time | G39: =RANDBETWEEN(6500,12000) -> 10977
A40: 38 | B40: Business Analyst | C40: Remote | D40: Athens, Attica, Greece | E40: DELIV1 | F40: Full time | G40: =RANDBETWEEN(6500,12000) -> 9608
A41: 39 | B41: Business Analyst | C41: On-site | D41: Astana, Aqmola oblısı, Kazakhstan | E41: TECH | F41: Full time | G41: =RANDBETWEEN(6500,12000) -> 11315
A42: 40 | B42: Business Analyst | C42: On-site | D42: North West, England, United Kingdom | E42: Change+ | G42: =RANDBETWEEN(6500,12000) -> 8500
A43: 41 | B43: Business Analyst | C43: Hybrid | D43: Berlin, Berlin, Germany | E43: Business & Organization | G43: =RANDBETWEEN(6500,12000) -> 7710
A44: 42 | B44: Business Analyst | C44: Remote | D44: Washington, District of Columbia, United States | E44: Account Team | F44: Full time | G44: =RANDBETWEEN(6500,12000) -> 6503
A45: 43 | B45: Business Analyst | C45: On-site | D45: Boston, Massachusetts, United States | E45: Delivery | F45: Full time | G45: =RANDBETWEEN(6500,12000) -> 11641
A46: 44 | B46: Business Analyst | C46: On-site | D46: Orlando, Florida, United States | E46: Information Technology | F46: Full time | G46: =RANDBETWEEN(6500,12000) -> 7402
A47: 45 | B47: Business Analyst | C47: On-site | D47: London, England, United Kingdom | E47: Change+ | G47: =RANDBETWEEN(6500,12000) -> 11952
A48: 46 | B48: Business Analyst | C48: Remote | D48: Makati, Metro Manila, Philippines | E48: Aux HQ | F48: Full time | G48: =RANDBETWEEN(6500,12000) -> 7639
A49: 47 | B49: Business Analyst | C49: On-site | D49: Washington, District of Columbia, United States | E49: Labs | F49: Full time | G49: =RANDBETWEEN(6500,12000) -> 8341
A50: 48 | B50: Business Analyst | C50: On-site | D50: Austin, Texas, United States | E50: Data Management | F50: Full time | G50: =RANDBETWEEN(6500,12000) -> 7696
A51: 49 | B51: Business Analyst | C51: On-site | D51: Brisbane, Queensland, Australia | E51: Australia Markets, Technical Services, Intelligence Workspace | F51: Full time | G51: =RANDBETWEEN(6500,12000) -> 8237
A52: 50 | B52: Business Analyst | C52: Hybrid | D52: Salt Lake City, Utah, United States | E52: Delivery | F52: Full time | G52: =RANDBETWEEN(6500,12000) -> 11521
A53: 51 | B53: Business Analyst | C53: Hybrid | D53: Vancouver, British Columbia, Canada | E53: Business Management | F53: Full time | G53: =RANDBETWEEN(6500,12000) -> 9019
A54: 52 | B54: Business Analyst | C54: Remote | D54: Edinburgh, Scotland, United Kingdom | E54: Business Services Professionals, Risk & Compliance | F54: Full time | G54: =RANDBETWEEN(6500,12000) -> 7277
A55: 53 | B55: Business Analyst | C55: On-site | D55: Swords, County Dublin, Ireland | E55: HR | F55: Full time | G55: =RANDBETWEEN(6500,12000) -> 9967
A56: 54 | B56: Business Analyst | C56: On-site | D56: London, England, United Kingdom | E56: Consultants, Advisory | F56: Full time | G56: =RANDBETWEEN(6500,12000) -> 9228
A57: 55 | B57: Business Analyst | C57: On-site | D57: London, England, United Kingdom | E57: Credit Risk | G57: =RANDBETWEEN(6500,12000) -> 10077
A58: 56 | B58: Business Analyst | C58: Hybrid | D58: Athens, Attica, Greece | E58: OPERATIONS | G58: =RANDBETWEEN(6500,12000) -> 11830
A59: 57 | B59: Business Analyst | C59: On-site | D59: Austin, Texas, United States | E59: Data Management | F59: Full time | G59: =RANDBETWEEN(6500,12000) -> 7408
A60: 58 | B60: Business Analyst | C60: On-site | D60: Brisbane, Queensland, Australia | E60: Australia Markets, Technical Services, Intelligence Workspace | F60: Full time | G60: =RANDBETWEEN(6500,12000) -> 10722
A61: 59 | B61: Business Analyst | C61: Hybrid | D61: Salt Lake City, Utah, United States | E61: Delivery | F61: Full time | G61: =RANDBETWEEN(6500,12000) -> 8537
A62: 60 | B62: Business Analyst | C62: Hybrid | D62: Vancouver, British Columbia, Canada | E62: Business Management | F62: Full time | G62: =RANDBETWEEN(6500,12000) -> 7261
A63: 61 | B63: Business Analyst | C63: Remote | D63: Edinburgh, Scotland, United Kingdom | E63: Business Services Professionals, Risk & Compliance | F63: Full time | G63: =RANDBETWEEN(6500,12000) -> 9888
A64: 62 | B64: Business Analyst | C64: On-site | D64: Swords, County Dublin, Ireland | E64: HR | F64: Full time | G64: =RANDBETWEEN(6500,12000) -> 6866
A65: 63 | B65: Business Analyst | C65: On-site | D65: London, England, United Kingdom | E65: Consultants, Advisory | F65: Full time | G65: =RANDBETWEEN(6500,12000) -> 7533
A66: 64 | B66: Business Analyst | C66: On-site | D66: London, England, United Kingdom | E66: Credit Risk | G66: =RANDBETWEEN(6500,12000) -> 9485
A67: 65 | B67: Business Analyst | C67: Hybrid | D67: Athens, Attica, Greece | E67: OPERATIONS | G67: =RANDBETWEEN(6500,12000) -> 9173
A68: 66 | B68: Business Analyst | C68: On-site | D68: Dublin, County Dublin, Ireland | E68: Ryanair Labs Dublin | F68: Full time | G68: =RANDBETWEEN(6500,12000) -> 10593
A69: 67 | B69: Business Analyst | C69: Hybrid | D69: London, England, United Kingdom | E69: Corporate Affairs | F69: Full time | G69: =RANDBETWEEN(6500,12000) -> 8221
A70: 68 | B70: Business Analyst | C70: On-site | D70: Hursley, England, United Kingdom | E70: Tech+ | G70: =RANDBETWEEN(6500,12000) -> 9561
A71: 69 | B71: Business Analyst | C71: On-site | D71: Sacramento, California, United States | E71: ITPM | F71: Full time | G71: =RANDBETWEEN(6500,12000) -> 10356
A72: 70 | B72: Business Analyst | C72: Hybrid | D72: Dublin, County Dublin, Ireland | E72: Product Delivery | F72: Full time | G72: =RANDBETWEEN(6500,12000) -> 8901
A73: 71 | B73: Business Analyst | C73: On-site | D73: Cambridge, England, United Kingdom | E73: Change+ | G73: =RANDBETWEEN(6500,12000) -> 11169
A74: 72 | B74: Business Analyst | C74: Remote | D74: Cherry Hill, New Jersey, United States | F74: Contract | G74: =RANDBETWEEN(6500,12000) -> 11899
A75: 73 | B75: Business Analyst | C75: On-site | D75: Orlando, Florida, United States | E75: Information Technology | F75: Full time | G75: =RANDBETWEEN(6500,12000) -> 11842
A76: 74 | B76: Business Analyst | C76: Hybrid | D76: Athens, Greece | E76: Information Technology | F76: Full time | G76: =RANDBETWEEN(6500,12000) -> 9226
A77: 75 | B77: Business Analyst | C77: On-site | D77: Dublin, County Dublin, Ireland | E77: Ryanair Labs Dublin | F77: Full time | G77: =RANDBETWEEN(6500,12000) -> 10048
A78: 76 | B78: Business Analyst | C78: Hybrid | D78: London, England, United Kingdom | E78: Corporate Affairs | F78: Full time | G78: =RANDBETWEEN(6500,12000) -> 8330
A79: 77 | B79: Business Analyst | C79: On-site | D79: Hursley, England, United Kingdom | E79: Tech+ | G79: =RANDBETWEEN(6500,12000) -> 10313
A80: 78 | B80: Business Analyst | D80: Sacramento, California, United States | E80: ITPM | F80: Full time | G80: =RANDBETWEEN(6500,12000) -> 10672
A81: 79 | B81: Business Analyst | C81: Hybrid | D81: Dublin, County Dublin, Ireland | E81: Product Delivery | F81: Full time | G81: =RANDBETWEEN(6500,12000) -> 6841
A82: 80 | B82: Business Analyst | C82: On-site | D82: Cambridge, England, United Kingdom | E82: Change+ | G82: =RANDBETWEEN(6500,12000) -> 8194
A83: 81 | B83: Business Analyst | C83: Remote | D83: Cherry Hill, New Jersey, United States | F83: Contract | G83: =RANDBETWEEN(6500,12000) -> 7414
A84: 82 | B84: Business Analyst | C84: On-site | D84: Orlando, Florida, United States | E84: Information Technology | F84: Full time | G84: =RANDBETWEEN(6500,12000) -> 10157
A85: 83 | B85: Business Analyst | C85: Hybrid | D85: Athens, Greece | E85: Information Technology | F85: Full time | G85: =RANDBETWEEN(6500,12000) -> 8807
A86: 84 | B86: Business Analyst | C86: On-site | D86: Dublin, County Dublin, Ireland | E86: Information Systems | F86: Full time | G86: =RANDBETWEEN(6500,12000) -> 9820
A87: 85 | B87: Business Analyst | C87: On-site | D87: Overland Park, Kansas, United States | E87: Consulting | F87: Contract | G87: =RANDBETWEEN(6500,12000) -> 8032
A88: 86 | B88: Business Analyst | C88: Hybrid | D88: Cary, North Carolina, United States | E88: 1 - Operations | F88: Full time | G88: =RANDBETWEEN(6500,12000) -> 7288
A89: 87 | B89: Business Analyst | C89: On-site | D89: Warrington, England, United Kingdom | E89: Data+ | F89: Full time | G89: =RANDBETWEEN(6500,12000) -> 10507
A90: 88 | B90: Business Analyst | C90: Remote | D90: France | E90: Marketing | F90: Full time | G90: =RANDBETWEEN(6500,12000) -> 6802
A91: 89 | B91: Business Analyst | C91: On-site | D91: Douala, Littoral, Cameroon | F91: Full time | G91: =RANDBETWEEN(6500,12000) -> 6949
A92: 90 | B92: Business Analyst | C92: Remote | D92: Cherry Hill, New Jersey, United States | F92: Contract | G92: =RANDBETWEEN(6500,12000) -> 7000
A93: 91 | B93: Business Analyst | C93: Remote | D93: Jordan | G93: =RANDBETWEEN(6500,12000) -> 7887
A94: 92 | B94: Business Analyst | C94: On-site | D94: Lagos, Lagos, Nigeria | E94: Information Technology | F94: Full time | G94: =RANDBETWEEN(6500,12000) -> 8025
A95: 93 | B95: Business Analyst | C95: On-site | D95: Amman, Amman Governorate, Jordan | E95: Sales, OLX Oman Jordan | F95: Full time | G95: =RANDBETWEEN(6500,12000) -> 8880
A96: 94 | B96: Business Analyst | C96: On-site | D96: Cebu City, Central Visayas, Philippines | F96: Full time | G96: =RANDBETWEEN(6500,12000) -> 9945
A97: 95 | B97: Business Analyst | C97: Remote | D97: London, England, United Kingdom | E97: Analytics | F97: Full time | G97: =RANDBETWEEN(6500,12000) -> 9531
A98: 96 | B98: Business Analyst | C98: Hybrid | D98: London, England, United Kingdom | E98: Finance | F98: Full time | G98: =RANDBETWEEN(6500,12000) -> 8837
A99: 97 | B99: Business Analyst | C99: Remote | D99: Belle Isle, Florida, United States | F99: Full time | G99: =RANDBETWEEN(6500,12000) -> 9382
A100: 98 | B100: Business Analyst | C100: Remote | D100: United States | E100: Computer/Software | F100: Full time | G100: =RANDBETWEEN(6500,12000) -> 7677
...

Sheet Dashboard
A2: Salarios | L2: Contratos
A3: Puesto | B3: Suma de Salarios | L3: Tipo | M3: Cantidad
A4: UI/UX | B4: 1817457 | L4: Tiempo completo | M4: =COUNTIF('Categoria x Puesto'!F:F,"Full time") -> 846
A5: Data Scientist | B5: 1754188 | L5: Contract | M5: =COUNTIF('Categoria x Puesto'!F:F,"Contract") -> 39
A6: Software Developer | B6: 1708647 | L6: Medio Tiempo | M6: =COUNTIF('Categoria x Puesto'!F:F,"Part time") -> 10
A7: HR | B7: 1668752 | L7: Temporal | M7: =COUNTIF('Categoria x Puesto'!F:F,"Temporary") -> 13
A8: Business Analyst | B8: 1616854 | L8: Temps plein | M8: =COUNTIF('Categoria x Puesto'!F:F,"Temps plein") -> 4
A9: Cloud | B9: 1570771 | L9: Otros | M9: =COUNTIF('Categoria x Puesto'!F:F,"Other") -> 14
M22: Cantidad de Trabajos
M23: Puestos | N23: Cantidad
M24: UI/UX | N24: =COUNTIF(job_data_merged_1[[#All],[Category]],"UI/UX") -> 191
M25: Data Scientist | N25: =COUNTIF(job_data_merged_1[[#All],[Category]],"Data Scientist") -> 190
M26: Software Developer | N26: =COUNTIF(job_data_merged_1[[#All],[Category]],"Software Developer") -> 189
A27: Modalidad de Trabajo | M27: HR | N27: =COUNTIF(job_data_merged_1[[#All],[Category]],"HR") -> 180
A28: Puesto | B28: Remoto | C28: Presencial | D28: Híbrido | M28: Business Analyst | N28: =COUNTIF(job_data_merged_1[[#All],[Category]],"Business Analyst") -> 175
A29: Business Analyst | B29: =COUNTIFS('Categoria x Puesto'!B:B,"Business Analyst",'Categoria x Puesto'!C:C,"Remote") -> 44 | C29: =COUNTIFS(job_data_merged_1[[#All],[Category]],"Business Analyst",job_data_merged_1[[#All],[Workplace]],"On-site") -> 90 | D29: =COUNTIFS(job_data_merged_1[[#All],[Category]],"Business Analyst",job_data_merged_1[[#All],[Workplace]],"Hybrid") -> 38 | M29: Cloud | N29: =COUNTIF(job_data_merged_1[[#All],[Category]],"Cloud") -> 170
A30: Cloud | B30: =COUNTIFS('Categoria x Puesto'!B:B,"Cloud",'Categoria x Puesto'!C:C,"Remote") -> 65 | C30: =COUNTIFS(job_data_merged_1[[#All],[Category]],"Cloud",job_data_merged_1[[#All],[Workplace]],"On-site") -> 62 | D30: =COUNTIFS(job_data_merged_1[[#All],[Category]],"Cloud",job_data_merged_1[[#All],[Workplace]],"Hybrid") -> 33
A31: Data Scientist | B31: =COUNTIFS('Categoria x Puesto'!B:B,"Data Scientist",'Categoria x Puesto'!C:C,"Remote") -> 71 | C31: =COUNTIFS(job_data_merged_1[[#All],[Category]],"Data Scientist",job_data_merged_1[[#All],[Workplace]],"On-site") -> 83 | D31: =COUNTIFS(job_data_merged_1[[#All],[Category]],"Data Scientist",job_data_merged_1[[#All],[Workplace]],"Hybrid") -> 24
A32: HR | B32: =COUNTIFS('Categoria x Puesto'!B:B,"HR",'Categoria x Puesto'!C:C,"Remote") -> 56 | C32: =COUNTIFS(job_data_merged_1[[#All],[Category]],"HR",job_data_merged_1[[#All],[Workplace]],"On-site") -> 96 | D32: =COUNTIFS(job_data_merged_1[[#All],[Category]],"HR",job_data_merged_1[[#All],[Workplace]],"Hybrid") -> 20
A33: Software Developer | B33: =COUNTIFS('Categoria x Puesto'!B:B,"Software Developer",'Categoria x Puesto'!C:C,"Remote") -> 70 | C33: =COUNTIFS(job_data_merged_1[[#All],[Category]],"Software Developer",job_data_merged_1[[#All],[Workplace]],"On-site") -> 80 | D33: =COUNTIFS(job_data_merged_1[[#All],[Category]],"Software Developer",job_data_merged_1[[#All],[Workplace]],"Hybrid") -> 21
A34: UI/UX | B34: =COUNTIFS('Categoria x Puesto'!B:B,"UI/UX",'Categoria x Puesto'!C:C,"Remote") -> 107 | C34: =COUNTIFS(job_data_merged_1[[#All],[Category]],"UI/UX",job_data_merged_1[[#All],[Workplace]],"On-site") -> 50 | D34: =COUNTIFS(job_data_merged_1[[#All],[Category]],"UI/UX",job_data_merged_1[[#All],[Workplace]],"Hybrid") -> 25
